setup.py
django_telegram_blog.egg-info/PKG-INFO
django_telegram_blog.egg-info/SOURCES.txt
django_telegram_blog.egg-info/dependency_links.txt
django_telegram_blog.egg-info/requires.txt
django_telegram_blog.egg-info/top_level.txt
telegram_blog/__init__.py
telegram_blog/admin.py
telegram_blog/apps.py
telegram_blog/models.py
telegram_blog/telegram.py
telegram_blog/tests.py
telegram_blog/urls.py
telegram_blog/utils.py
telegram_blog/views.py
telegram_blog/management/__init__.py
telegram_blog/management/commands/__init__.py
telegram_blog/management/commands/telegramblogsetwebhook.py
telegram_blog/management/commands/telegramblogupdater.py
telegram_blog/migrations/0001_initial.py
telegram_blog/migrations/0002_auto_20180906_1654.py
telegram_blog/migrations/__init__.py
telegram_blog/templates/telegram_blog/base.html
telegram_blog/templates/telegram_blog/blog_detail.html
telegram_blog/templates/telegram_blog/entry_audio.html
telegram_blog/templates/telegram_blog/entry_document.html
telegram_blog/templates/telegram_blog/entry_location.html
telegram_blog/templates/telegram_blog/entry_photo.html
telegram_blog/templates/telegram_blog/entry_sticker.html
telegram_blog/templates/telegram_blog/entry_text.html
telegram_blog/templates/telegram_blog/entry_venue.html
telegram_blog/templates/telegram_blog/entry_video.html
telegram_blog/templates/telegram_blog/entry_video_note.html
telegram_blog/templates/telegram_blog/entry_voice.html
telegram_blog/templates/telegram_blog/index.html
telegram_blog/templatetags/__init__.py
telegram_blog/templatetags/telegram_blog.py