Metadata-Version: 1.0
Name: django-telegram-blog
Version: 0.6.2
Summary: Blogging for Django via Telegram
Home-page: UNKNOWN
Author: Jaco du Plessis
Author-email: jaco@jacoduplessis.co.za
License: MIT
Platform: UNKNOWN
